[
  {
    "cast_hash": "0x3c09e912",
    "url": "https://warpcast.com/dwr.eth/0x3c09e912",
    "author_username": "dwr.eth",
    "show_date": "2024-02-07",
    "show_title": "GM Farcaster ep58, Feb 7, 2024",
    "source_episode_id": "OcxOrKNO6ak",
    "author_fid": 3,
    "author_pfp": "https://imagedelivery.net/BXluQx4ige9GuW0Ia56BHw/bc698287-5adc-4cc5-a503-de16963ed900/original",
    "cast_date": "2024-02-06T16:01:00.000Z",
    "text": "61K DAU yesterday!\n\n40% day over day growth!\n\n10x DAU growth in 14 days!",
    "embeds": [
      {
        "url": "https://i.imgur.com/mc6UNQI.png",
        "metadata": {
          "content_type": "image/png",
          "content_length": 17023,
          "_status": "RESOLVED",
          "image": {
            "width_px": 312,
            "height_px": 388
          }
        }
      }
    ],
    "enrichment_status": "SUCCESS"
  },
  {
    "cast_hash": "0xdde98e91",
    "url": "https://warpcast.com/dwr.eth/0xdde98e91",
    "author_username": "dwr.eth",
    "show_date": "2024-02-07",
    "show_title": "GM Farcaster ep58, Feb 7, 2024",
    "source_episode_id": "OcxOrKNO6ak",
    "author_fid": 3,
    "author_pfp": "https://imagedelivery.net/BXluQx4ige9GuW0Ia56BHw/bc698287-5adc-4cc5-a503-de16963ed900/original",
    "cast_date": "2024-02-06T03:40:51.000Z",
    "text": "More DAU today than January 2024 MAU and 2023 YAU!",
    "embeds": [],
    "enrichment_status": "SUCCESS"
  },
  {
    "cast_hash": "0xac490bf0",
    "url": "https://warpcast.com/dwr.eth/0xac490bf0",
    "author_username": "dwr.eth",
    "show_date": "2024-02-07",
    "show_title": "GM Farcaster ep58, Feb 7, 2024",
    "source_episode_id": "OcxOrKNO6ak",
    "author_fid": 3,
    "author_pfp": "https://imagedelivery.net/BXluQx4ige9GuW0Ia56BHw/bc698287-5adc-4cc5-a503-de16963ed900/original",
    "cast_date": "2024-02-06T03:20:45.000Z",
    "text": "Flipped Twitter! Finally made it to the far side 😈",
    "embeds": [
      {
        "url": "https://i.imgur.com/fUsOd2S.png",
        "metadata": {
          "content_type": "image/png",
          "content_length": 26452,
          "_status": "RESOLVED",
          "image": {
            "width_px": 1102,
            "height_px": 340
          }
        }
      }
    ],
    "enrichment_status": "SUCCESS"
  },
  {
    "cast_hash": "0x51d63a42",
    "url": "https://warpcast.com/dwr.eth/0x51d63a42",
    "author_username": "dwr.eth",
    "show_date": "2024-02-07",
    "show_title": "GM Farcaster ep58, Feb 7, 2024",
    "source_episode_id": "OcxOrKNO6ak",
    "author_fid": 3,
    "author_pfp": "https://imagedelivery.net/BXluQx4ige9GuW0Ia56BHw/bc698287-5adc-4cc5-a503-de16963ed900/original",
    "cast_date": "2024-02-06T03:24:43.000Z",
    "text": "",
    "embeds": [
      {
        "url": "https://i.imgur.com/mOkfMTA.jpg",
        "metadata": {
          "content_type": "image/jpeg",
          "content_length": 48341,
          "_status": "RESOLVED",
          "image": {
            "width_px": 800,
            "height_px": 450
          }
        }
      },
      {
        "cast_id": {
          "fid": 7258,
          "hash": "0x095bc56e4f58da369c27a42c32553bd125252ca7"
        },
        "cast": {
          "object": "cast_embedded",
          "hash": "0x095bc56e4f58da369c27a42c32553bd125252ca7",
          "author": {
            "object": "user_dehydrated",
            "fid": 7258,
            "username": "riotgoools",
            "display_name": "elle",
            "pfp_url": "https://i.imgur.com/gYX0Qdy.png",
            "custody_address": "0x91f44731d8bffea85cc5c117e411ffdb7c5732f4"
          },
          "app": {
            "object": "user_dehydrated",
            "fid": 9152,
            "username": "warpcast",
            "display_name": "Warpcast",
            "pfp_url": "https://i.imgur.com/3d6fFAI.png",
            "custody_address": "0x02ef790dd7993a35fd847c053eddae940d055596"
          },
          "thread_hash": "0x6823605763e1aca36fdffa44ade8c4d843a5fda4",
          "parent_hash": "0x6823605763e1aca36fdffa44ade8c4d843a5fda4",
          "parent_url": null,
          "root_parent_url": null,
          "parent_author": {
            "fid": 3
          },
          "text": "is it weird that we released this only 2 months ago and it already feels so nostalgic (ಥ◡ಥ) wowow, co2, farcaster pants emoji...",
          "timestamp": "2024-02-06T03:22:59.000Z",
          "embeds": [],
          "channel": null
        }
      }
    ],
    "enrichment_status": "SUCCESS"
  },
  {
    "cast_hash": "0xcf8ed1d3",
    "url": "https://warpcast.com/coopahtroopa.eth/0xcf8ed1d3",
    "author_username": "coopahtroopa.eth",
    "show_date": "2024-02-07",
    "show_title": "GM Farcaster ep58, Feb 7, 2024",
    "source_episode_id": "OcxOrKNO6ak",
    "author_fid": 206,
    "author_pfp": "https://i.imgur.com/0NB7bxd.gif",
    "cast_date": "2024-02-06T04:04:35.000Z",
    "text": "The best way to grow a following on FC is to create meaningful conversation.\n\nSounds obvious but you'd be surprised by how many amazing people here are able to hold deep conversations about whatever is on your mind.\n\nPut real time and energy into the network and you will be rewarded.",
    "embeds": [],
    "enrichment_status": "SUCCESS"
  },
  {
    "cast_hash": "0xefc81ad0",
    "url": "https://warpcast.com/dwr.eth/0xefc81ad0",
    "author_username": "dwr.eth",
    "show_date": "2024-02-07",
    "show_title": "GM Farcaster ep58, Feb 7, 2024",
    "source_episode_id": "OcxOrKNO6ak",
    "author_fid": 3,
    "author_pfp": "https://imagedelivery.net/BXluQx4ige9GuW0Ia56BHw/bc698287-5adc-4cc5-a503-de16963ed900/original",
    "cast_date": "2024-02-05T16:21:40.000Z",
    "text": "PSA -- I *won't* be at ETHDenver. :)",
    "embeds": [],
    "enrichment_status": "SUCCESS"
  },
  {
    "cast_hash": "0xfc2666ee",
    "url": "https://warpcast.com/nounishprof/0xfc2666ee",
    "author_username": "nounishprof",
    "show_date": "2024-02-07",
    "show_title": "GM Farcaster ep58, Feb 7, 2024",
    "source_episode_id": "OcxOrKNO6ak",
    "author_fid": 4167,
    "author_pfp": "https://imagedelivery.net/BXluQx4ige9GuW0Ia56BHw/0e0686be-ae1a-47d2-c737-5beecfe21700/rectcrop3",
    "cast_date": "2024-02-06T13:11:53.000Z",
    "text": "PSA — @adrienne and I *will* and oh do we have plans for y’all!",
    "embeds": [
      {
        "cast_id": {
          "fid": 3,
          "hash": "0xefc81ad0dc89ee2a8471624f8b97560e3951de95"
        },
        "cast": {
          "object": "cast_embedded",
          "hash": "0xefc81ad0dc89ee2a8471624f8b97560e3951de95",
          "author": {
            "object": "user_dehydrated",
            "fid": 3,
            "username": "dwr.eth",
            "display_name": "Dan Romero",
            "pfp_url": "https://imagedelivery.net/BXluQx4ige9GuW0Ia56BHw/bc698287-5adc-4cc5-a503-de16963ed900/original",
            "custody_address": "0x6b0bda3f2ffed5efc83fa8c024acff1dd45793f1"
          },
          "app": {
            "object": "user_dehydrated",
            "fid": 9152,
            "username": "warpcast",
            "display_name": "Warpcast",
            "pfp_url": "https://i.imgur.com/3d6fFAI.png",
            "custody_address": "0x02ef790dd7993a35fd847c053eddae940d055596"
          },
          "thread_hash": "0xefc81ad0dc89ee2a8471624f8b97560e3951de95",
          "parent_hash": null,
          "parent_url": null,
          "root_parent_url": null,
          "parent_author": {
            "fid": null
          },
          "text": "PSA -- I *won't* be at ETHDenver. :)",
          "timestamp": "2024-02-05T16:21:40.000Z",
          "embeds": [],
          "channel": null
        }
      }
    ],
    "enrichment_status": "SUCCESS"
  },
  {
    "cast_hash": "0xb11100d8",
    "url": "https://warpcast.com/michael/0xb11100d8",
    "author_username": "michael",
    "show_date": "2024-02-07",
    "show_title": "GM Farcaster ep58, Feb 7, 2024",
    "source_episode_id": "OcxOrKNO6ak",
    "author_fid": 2723,
    "author_pfp": "https://i.imgur.com/rISu0sh.jpg",
    "cast_date": "2024-02-06T15:52:30.000Z",
    "text": "Introducing event frames!\n\nTo create a frame, just post a link from any event on our events page, platform.serotonin.co/events\n\nFor instance, planning to attend ETH Denver?\n\nhttps://platform.serotonin.co/events/ethdenver-2024-denver-us-45\n\nmore info: https://warpcast.com/michael/0xbda1f6ad",
    "embeds": [
      {
        "url": "https://platform.serotonin.co/events/ethdenver-2024-denver-us-45",
        "metadata": {
          "content_type": "text/html;charset=utf-8",
          "content_length": null,
          "_status": "RESOLVED",
          "html": {
            "favicon": "/favicon.ico",
            "ogImage": [
              {
                "url": "https://platform.serotonin.co/api/events/ethdenver-2024-denver-us-45/og?name=ETHDenver+2024&city=Denver&state=&country=United+States&startDate=2024-02-23T00%3A00%3A00.000Z&endDate=2024-03-03T00%3A00%3A00.000Z&totalAttendees=662&bannerImage=https%3A%2F%2Fimages.unsplash.com%2Fphoto-1573297627466-6bed413a43f1%3Fq%3D80%26w%3D2832%26auto%3Dformat%26fit%3Dcrop%26ixlib%3Drb-4.0.3%26ixid%3DM3wxMjA3fDB8MHxwaG90by1wYWdlfHx8fGVufDB8fHx8fA%253D%253D&avatarImage=&timezone=UTC&isVirtual=false&isAllDay=true&parentEventName=&organizer=&variant=default"
              }
            ],
            "ogTitle": "ETHDenver 2024 | Serotonin",
            "ogLocale": "en",
            "ogDescription": "ETHDenver is recognized as the world's largest Web3 #BUIDLathon (formerly known\nas a hackathon). It caters to enthusiast..."
          }
        }
      }
    ],
    "enrichment_status": "SUCCESS"
  },
  {
    "cast_hash": "0x3d877465",
    "url": "https://warpcast.com/nounishprof/0x3d877465",
    "author_username": "nounishprof",
    "show_date": "2024-02-07",
    "show_title": "GM Farcaster ep58, Feb 7, 2024",
    "source_episode_id": "OcxOrKNO6ak",
    "author_fid": 4167,
    "author_pfp": "https://imagedelivery.net/BXluQx4ige9GuW0Ia56BHw/0e0686be-ae1a-47d2-c737-5beecfe21700/rectcrop3",
    "cast_date": "2024-02-06T16:33:39.000Z",
    "text": "OMG the queen is here! 👸Let’s get her to 400 ASAP! Look alive girls — it’s happening! \n\nAnd Betty - this is FarcastHER —yes the boys can post here too but the vibes are kept immaculate by @adrienne and frens like @ted — go follow all the amazing builders posting in this channel and WELCOME! 💜",
    "embeds": [
      {
        "cast_id": {
          "fid": 15900,
          "hash": "0x87bb39622199ea4c8aae13770e7b0bf83d282eef"
        },
        "cast": {
          "object": "cast_embedded",
          "hash": "0x87bb39622199ea4c8aae13770e7b0bf83d282eef",
          "author": {
            "object": "user_dehydrated",
            "fid": 15900,
            "username": "betty",
            "display_name": "Betty",
            "pfp_url": "https://i.imgur.com/pMDcAmR.jpg",
            "custody_address": "0xb2a2ce9611f6482cf52e9876337b0ab083231a03"
          },
          "app": {
            "object": "user_dehydrated",
            "fid": 9152,
            "username": "warpcast",
            "display_name": "Warpcast",
            "pfp_url": "https://i.imgur.com/3d6fFAI.png",
            "custody_address": "0x02ef790dd7993a35fd847c053eddae940d055596"
          },
          "thread_hash": "0x87bb39622199ea4c8aae13770e7b0bf83d282eef",
          "parent_hash": null,
          "parent_url": null,
          "root_parent_url": null,
          "parent_author": {
            "fid": null
          },
          "text": "What is a cast? What is a warp? Help. 😂",
          "timestamp": "2024-02-06T15:52:14.000Z",
          "embeds": [],
          "channel": null
        }
      }
    ],
    "enrichment_status": "SUCCESS"
  },
  {
    "cast_hash": "0x7b40c7e9",
    "url": "https://warpcast.com/nounishprof/0x7b40c7e9",
    "author_username": "nounishprof",
    "show_date": "2024-02-07",
    "show_title": "GM Farcaster ep58, Feb 7, 2024",
    "source_episode_id": "OcxOrKNO6ak",
    "author_fid": 4167,
    "author_pfp": "https://imagedelivery.net/BXluQx4ige9GuW0Ia56BHw/0e0686be-ae1a-47d2-c737-5beecfe21700/rectcrop3",
    "cast_date": "2024-02-06T16:47:56.000Z",
    "text": "warp liberally \n\n(great way to welcome the newbies —well the ones we like anyway)",
    "embeds": [
      {
        "url": "https://i.imgur.com/vv3D9z9.jpg",
        "metadata": {
          "content_type": "image/jpeg",
          "content_length": 197251,
          "_status": "RESOLVED",
          "image": {
            "width_px": 1021,
            "height_px": 671
          }
        }
      }
    ],
    "enrichment_status": "SUCCESS"
  },
  {
    "cast_hash": "0xd9a03543",
    "url": "https://warpcast.com/ted/0xd9a03543",
    "author_username": "ted",
    "show_date": "2024-02-07",
    "show_title": "GM Farcaster ep58, Feb 7, 2024",
    "source_episode_id": "OcxOrKNO6ak",
    "author_fid": 239,
    "author_pfp": "https://openseauserdata.com/files/fd28c65d9b5192168fb259009a3afd36.png",
    "cast_date": "2024-02-05T04:34:44.000Z",
    "text": "decide who will have to hit the dance floor first at FarCon between @dwr.eth vs. @v (since qDAU will be at 100k+ by then).\n\ncast your vote w/ mint:\nzora.co/collect/base:0xf569a12768a050eab250aa3cc71d53564ce6e349/1\nzora.co/collect/base:0xf569a12768a050eab250aa3cc71d53564ce6e349/2\n\nsry dwr + v i shouldve asked permission",
    "embeds": [
      {
        "url": "http://zora.co/collect/base:0xf569a12768a050eab250aa3cc71d53564ce6e349/1",
        "metadata": {
          "content_type": "text/html;charset=utf-8",
          "content_length": null,
          "_status": "RESOLVED",
          "html": {
            "ogUrl": "https://zora.co/collect/base:0xf569a12768a050eab250aa3cc71d53564ce6e349/1",
            "favicon": "https://zora.co/favicon/favicon.png",
            "ogImage": [
              {
                "url": "https://zora.co/api/og-image/post/base:0xf569a12768a050eab250aa3cc71d53564ce6e349/1?v=2&mints=70"
              }
            ],
            "ogTitle": "V BREAKS THE INTERNET",
            "ogLocale": "en",
            "ogSiteName": "Zora",
            "fcFrame": {
              "button": {
                "title": "Buy",
                "action": {
                  "url": "https://zora.co/collect/base:0xf569a12768a050eab250aa3cc71d53564ce6e349/1/frame-v2",
                  "name": "Buy",
                  "type": "launch_frame",
                  "splashImageUrl": "https://zora.co/assets/logo.png",
                  "splashBackgroundColor": "#ffffff"
                }
              },
              "version": "next",
              "imageUrl": "https://zora.co/api/og-image/post/base:0xf569a12768a050eab250aa3cc71d53564ce6e349/1?v=2&mints=70&crop=farcaster"
            }
          },
          "frame": {
            "version": "next",
            "title": "Buy",
            "image": "https://zora.co/api/og-image/post/base:0xf569a12768a050eab250aa3cc71d53564ce6e349/1?v=2&mints=70&crop=farcaster",
            "frames_url": "http://zora.co/collect/base:0xf569a12768a050eab250aa3cc71d53564ce6e349/1"
          }
        }
      },
      {
        "url": "http://zora.co/collect/base:0xf569a12768a050eab250aa3cc71d53564ce6e349/2",
        "metadata": {
          "content_type": "text/html;charset=utf-8",
          "content_length": null,
          "_status": "RESOLVED",
          "html": {
            "ogUrl": "https://zora.co/collect/base:0xf569a12768a050eab250aa3cc71d53564ce6e349/2",
            "favicon": "https://zora.co/favicon/favicon.png",
            "ogImage": [
              {
                "url": "https://zora.co/api/og-image/post/base:0xf569a12768a050eab250aa3cc71d53564ce6e349/2?v=2&mints=72"
              }
            ],
            "ogTitle": "DWR BREAKS THE INTERNET",
            "ogLocale": "en",
            "ogSiteName": "Zora",
            "fcFrame": {
              "button": {
                "title": "Buy",
                "action": {
                  "url": "https://zora.co/collect/base:0xf569a12768a050eab250aa3cc71d53564ce6e349/2/frame-v2",
                  "name": "Buy",
                  "type": "launch_frame",
                  "splashImageUrl": "https://zora.co/assets/logo.png",
                  "splashBackgroundColor": "#ffffff"
                }
              },
              "version": "next",
              "imageUrl": "https://zora.co/api/og-image/post/base:0xf569a12768a050eab250aa3cc71d53564ce6e349/2?v=2&mints=72&crop=farcaster"
            }
          },
          "frame": {
            "version": "next",
            "title": "Buy",
            "image": "https://zora.co/api/og-image/post/base:0xf569a12768a050eab250aa3cc71d53564ce6e349/2?v=2&mints=72&crop=farcaster",
            "frames_url": "http://zora.co/collect/base:0xf569a12768a050eab250aa3cc71d53564ce6e349/2"
          }
        }
      }
    ],
    "enrichment_status": "SUCCESS"
  },
  {
    "cast_hash": "0xdb729364",
    "url": "https://warpcast.com/gabrielayuso.eth/0xdb729364",
    "author_username": "gabrielayuso.eth",
    "show_date": "2024-02-07",
    "show_title": "GM Farcaster ep58, Feb 7, 2024",
    "source_episode_id": "OcxOrKNO6ak",
    "author_fid": 834,
    "author_pfp": "https://imagedelivery.net/BXluQx4ige9GuW0Ia56BHw/0a4721e1-7694-44c0-f120-4eec4f747300/original",
    "cast_date": "2024-02-04T19:34:12.000Z",
    "text": "",
    "embeds": [
      {
        "cast_id": {
          "fid": 834,
          "hash": "0x7f4510532c7afc914a18a49822ab259e2032b868"
        },
        "cast": {
          "object": "cast_embedded",
          "hash": "0x7f4510532c7afc914a18a49822ab259e2032b868",
          "author": {
            "object": "user_dehydrated",
            "fid": 834,
            "username": "gabrielayuso.eth",
            "display_name": "Gabriel Ayuso",
            "pfp_url": "https://imagedelivery.net/BXluQx4ige9GuW0Ia56BHw/0a4721e1-7694-44c0-f120-4eec4f747300/original",
            "custody_address": "0xf8381127c3bec4162f7fceaf13709c249b8b87e2"
          },
          "app": {
            "object": "user_dehydrated",
            "fid": 9152,
            "username": "warpcast",
            "display_name": "Warpcast",
            "pfp_url": "https://i.imgur.com/3d6fFAI.png",
            "custody_address": "0x02ef790dd7993a35fd847c053eddae940d055596"
          },
          "thread_hash": "0x7f4510532c7afc914a18a49822ab259e2032b868",
          "parent_hash": null,
          "parent_url": "chain://eip155:1/erc721:0xfd8427165df67df6d7fd689ae67c8ebf56d9ca61",
          "root_parent_url": "chain://eip155:1/erc721:0xfd8427165df67df6d7fd689ae67c8ebf56d9ca61",
          "parent_author": {
            "fid": null
          },
          "text": "",
          "timestamp": "2024-02-04T19:33:54.000Z",
          "embeds": [
            {
              "url": "https://i.imgur.com/zaR79A9.jpg",
              "metadata": {
                "content_type": "image/jpeg",
                "content_length": 100290,
                "_status": "RESOLVED",
                "image": {
                  "width_px": 914,
                  "height_px": 499
                }
              }
            }
          ],
          "channel": {
            "object": "channel_dehydrated",
            "id": "memes",
            "name": "Memes",
            "image_url": "https://i.seadn.io/gcs/files/1f4acfc1e6831eb38e9453ce34ac79f8.png?auto=format&dpr=1&w=512"
          }
        }
      }
    ],
    "enrichment_status": "SUCCESS"
  },
  {
    "cast_hash": "0xd0cd3fe4",
    "url": "https://warpcast.com/whit/0xd0cd3fe4",
    "author_username": "whit",
    "show_date": "2024-02-07",
    "show_title": "GM Farcaster ep58, Feb 7, 2024",
    "source_episode_id": "OcxOrKNO6ak",
    "author_fid": 4583,
    "author_pfp": "https://imagedelivery.net/BXluQx4ige9GuW0Ia56BHw/6c28d2f0-3e88-4f51-b988-bd1fd8513c00/rectcrop3",
    "cast_date": "2024-02-06T15:17:21.000Z",
    "text": "Do I want Farcaster to succeed? YES\nAm I a snob? ALSO YES",
    "embeds": [
      {
        "url": "https://i.imgur.com/BiWKbny.jpg",
        "metadata": {
          "content_type": "image/jpeg",
          "content_length": 317334,
          "_status": "RESOLVED",
          "image": {
            "width_px": 1111,
            "height_px": 1476
          }
        }
      }
    ],
    "enrichment_status": "SUCCESS"
  },
  {
    "cast_hash": "0x26eca6b9",
    "url": "https://warpcast.com/linda/0x26eca6b9",
    "author_username": "linda",
    "show_date": "2024-02-07",
    "show_title": "GM Farcaster ep58, Feb 7, 2024",
    "source_episode_id": "OcxOrKNO6ak",
    "author_fid": 12,
    "author_pfp": "https://imagedelivery.net/BXluQx4ige9GuW0Ia56BHw/6aa18817-6238-4b25-086f-1edd0c438f00/original",
    "cast_date": "2024-02-07T01:41:04.000Z",
    "text": "I just had a weird experience posting on X / Twitter where I was trying to think of which channel my post belong to and then I realized that I was not on Farcaster 😂",
    "embeds": [],
    "enrichment_status": "SUCCESS"
  },
  {
    "cast_hash": "0x806f37d6",
    "url": "https://warpcast.com/v/0x806f37d6",
    "author_username": "v",
    "show_date": "2024-02-07",
    "show_title": "GM Farcaster ep58, Feb 7, 2024",
    "source_episode_id": "OcxOrKNO6ak",
    "author_fid": 2,
    "author_pfp": "https://i.seadn.io/gae/sYAr036bd0bRpj7OX6B-F-MqLGznVkK3--DSneL_BT5GX4NZJ3Zu91PgjpD9-xuVJtHq0qirJfPZeMKrahz8Us2Tj_X8qdNPYC-imqs?w=500&auto=format",
    "cast_date": "2024-02-07T01:25:59.000Z",
    "text": "all part of the secret master plan",
    "embeds": [
      {
        "url": "https://i.imgur.com/FktNVZi.png",
        "metadata": {
          "content_type": "image/png",
          "content_length": 73028,
          "_status": "RESOLVED",
          "image": {
            "width_px": 1234,
            "height_px": 352
          }
        }
      }
    ],
    "enrichment_status": "SUCCESS"
  },
  {
    "cast_hash": "0x66737964",
    "url": "https://warpcast.com/cameron/0x66737964",
    "author_username": "cameron",
    "show_date": "2024-02-07",
    "show_title": "GM Farcaster ep58, Feb 7, 2024",
    "source_episode_id": "OcxOrKNO6ak",
    "author_fid": 617,
    "author_pfp": "https://imagedelivery.net/BXluQx4ige9GuW0Ia56BHw/ac4e8cdc-f317-4711-d742-bb59c4651d00/original",
    "cast_date": "2024-02-05T13:35:34.000Z",
    "text": "Waking up to the Trending tab vibe shift on NewUserpocalypse Monday",
    "embeds": [
      {
        "url": "https://i.imgur.com/Ti3x4Wf.jpg",
        "metadata": {
          "content_type": "image/jpeg",
          "content_length": 195506,
          "_status": "RESOLVED",
          "image": {
            "width_px": 600,
            "height_px": 284
          }
        }
      }
    ],
    "enrichment_status": "SUCCESS"
  },
  {
    "cast_hash": "0xedc32c91",
    "url": "https://warpcast.com/v/0xedc32c91",
    "author_username": "v",
    "show_date": "2024-02-07",
    "show_title": "GM Farcaster ep58, Feb 7, 2024",
    "source_episode_id": "OcxOrKNO6ak",
    "author_fid": 2,
    "author_pfp": "https://i.seadn.io/gae/sYAr036bd0bRpj7OX6B-F-MqLGznVkK3--DSneL_BT5GX4NZJ3Zu91PgjpD9-xuVJtHq0qirJfPZeMKrahz8Us2Tj_X8qdNPYC-imqs?w=500&auto=format",
    "cast_date": "2024-02-07T01:48:45.000Z",
    "text": "Frames now support easy links! \n\nCreate buttons that link to pages in 3 lines of code. \n\nFull spec here: https://warpcast.notion.site/Frames-External-Links-Public-60c9900cffae4e2fb1b6aae3d4601c15?pvs=4\n\nh/t @horsefacts.eth and @deodad for this!",
    "embeds": [
      {
        "url": "https://i.imgur.com/faiq3Fl.png",
        "metadata": {
          "content_type": "image/png",
          "content_length": 127874,
          "_status": "RESOLVED",
          "image": {
            "width_px": 1538,
            "height_px": 386
          }
        }
      },
      {
        "url": "https://warpcast.notion.site/Frames-External-Links-Public-60c9900cffae4e2fb1b6aae3d4601c15?pvs=4",
        "metadata": {
          "content_type": "text/html;charset=utf-8",
          "content_length": null,
          "_status": "RESOLVED",
          "html": {
            "ogUrl": "https://warpcast.notion.site/Frames-External-Links-Public-60c9900cffae4e2fb1b6aae3d4601c15",
            "ogType": "article",
            "favicon": "https://warpcast.notion.site/images/favicon.ico",
            "ogImage": [
              {
                "url": "https://warpcast.notion.site/images/meta/notion-wordmark.png",
                "type": "png"
              }
            ],
            "ogTitle": "Frames: External Links [Public] | Notion",
            "ogLocale": "en_US",
            "ogSiteName": "Warpcast on Notion",
            "ogDescription": "Goals"
          }
        }
      }
    ],
    "enrichment_status": "SUCCESS"
  },
  {
    "cast_hash": "0x6ab42a45",
    "url": "https://warpcast.com/tinyrainboot/0x6ab42a45",
    "author_username": "tinyrainboot",
    "show_date": "2024-02-07",
    "show_title": "GM Farcaster ep58, Feb 7, 2024",
    "source_episode_id": "OcxOrKNO6ak",
    "author_fid": 9218,
    "author_pfp": "https://imagedelivery.net/BXluQx4ige9GuW0Ia56BHw/050e639e-c544-4c63-2d50-8cb9d9b01200/original",
    "cast_date": "2024-02-05T07:10:33.000Z",
    "text": "Hi! I’m tinyrainboot. I’m a new media artist, meaning I tend to stick to digitally native methods of creation these days. My work focuses on themes of dreams, nostalgia, fantasy, stepping into who you want to be, and the belief that this can’t be all there is. 💕",
    "embeds": [
      {
        "url": "https://i.imgur.com/ij1qfLZ.jpg",
        "metadata": {
          "content_type": "image/jpeg",
          "content_length": 162797,
          "_status": "RESOLVED",
          "image": {
            "width_px": 1900,
            "height_px": 1065
          }
        }
      }
    ],
    "enrichment_status": "SUCCESS"
  },
  {
    "cast_hash": "0x9e2c692a",
    "url": "https://warpcast.com/dwr.eth/0x9e2c692a",
    "author_username": "dwr.eth",
    "show_date": "2024-02-07",
    "show_title": "GM Farcaster ep58, Feb 7, 2024",
    "source_episode_id": "OcxOrKNO6ak",
    "author_fid": 3,
    "author_pfp": "https://imagedelivery.net/BXluQx4ige9GuW0Ia56BHw/bc698287-5adc-4cc5-a503-de16963ed900/original",
    "cast_date": "2024-02-06T21:12:50.000Z",
    "text": "Weekly Mint with Warps\n\nfarout by @usersteen.eth\n\nhttps://zora.co/collect/zora:0xd60ce20317b7bfa9ed8dba9215b756001810faea/2",
    "embeds": [
      {
        "url": "https://zora.co/collect/zora:0xd60ce20317b7bfa9ed8dba9215b756001810faea/2?referrer=0xBe3FC886e104904935cfC5f4F32F4CCec06CbA79",
        "metadata": {
          "_status": "PENDING"
        }
      }
    ],
    "enrichment_status": "SUCCESS"
  },
  {
    "cast_hash": "0x0d427884",
    "url": "https://warpcast.com/dwr.eth/0x0d427884",
    "author_username": "dwr.eth",
    "show_date": "2024-02-07",
    "show_title": "GM Farcaster ep58, Feb 7, 2024",
    "source_episode_id": "OcxOrKNO6ak",
    "author_fid": 3,
    "author_pfp": "https://imagedelivery.net/BXluQx4ige9GuW0Ia56BHw/bc698287-5adc-4cc5-a503-de16963ed900/original",
    "cast_date": "2024-02-04T01:13:32.000Z",
    "text": "Farcaster requires proof of work.",
    "embeds": [],
    "enrichment_status": "SUCCESS"
  },
  {
    "cast_hash": "0x210b5267",
    "url": "https://warpcast.com/jess/0x210b5267",
    "author_username": "jess",
    "show_date": "2024-02-07",
    "show_title": "GM Farcaster ep58, Feb 7, 2024",
    "source_episode_id": "OcxOrKNO6ak",
    "author_fid": 139,
    "author_pfp": "https://i.imgur.com/KkyGJLy.jpg",
    "cast_date": "2024-01-30T04:28:25.000Z",
    "text": "Farcaster 101\n\nNew here? 6 tips to getting the most out of FC\n\n1. Cast to get you Active Badge\n2. Get the most out of channels\n3. Understand Warps\n4. Follow the engaging casters\n5. Wrap your head around frames\n6. Explore other clients and apps \n\nI get into the details of these and more below 👇",
    "embeds": [],
    "enrichment_status": "SUCCESS"
  },
  {
    "cast_hash": "0xd525a05b",
    "url": "https://warpcast.com/christin/0xd525a05b",
    "author_username": "christin",
    "show_date": "2024-02-07",
    "show_title": "GM Farcaster ep58, Feb 7, 2024",
    "source_episode_id": "OcxOrKNO6ak",
    "author_fid": 15850,
    "author_pfp": "https://imagedelivery.net/BXluQx4ige9GuW0Ia56BHw/3bd90b57-732c-445b-4670-00040e540100/original",
    "cast_date": "2024-02-02T19:44:13.000Z",
    "text": "I’ve been thinking about how to enjoy Warpcast without the agitation that comes with new commotions\n\nLove the new features and will use them, though the buzz can sometimes degrade my feed experience \n\nWhat has helped:\n1) browsing cozy channels like /costco and /sardines , fewer casts per day\n2) un-follow high spam..",
    "embeds": [],
    "enrichment_status": "SUCCESS"
  },
  {
    "cast_hash": "0x91141ee5",
    "url": "https://warpcast.com/emmanuel/0x91141ee5",
    "author_username": "emmanuel",
    "show_date": "2024-02-07",
    "show_title": "GM Farcaster ep58, Feb 7, 2024",
    "source_episode_id": "OcxOrKNO6ak",
    "author_fid": 16877,
    "author_pfp": "https://imagedelivery.net/BXluQx4ige9GuW0Ia56BHw/feb3c6cc-0e09-4137-b80e-821a83a79500/rectcrop3",
    "cast_date": "2024-02-04T07:08:38.000Z",
    "text": "farcaster tip for newbies:\n\nfarcaster is the protocol.\n\nwarpcast is the client.\n\nthink of farcaster as Italy and warpcast as your tour guide.\n\nthere's only one Italy, but lots of other tour guides, such as @super, @farquest, @yup, among others.\n\na great resource for this: https://github.com/a16z/awesome-farcaster",
    "embeds": [
      {
        "url": "https://github.com/a16z/awesome-farcaster",
        "metadata": {
          "content_type": "text/html;charset=utf-8",
          "content_length": null,
          "_status": "RESOLVED",
          "html": {
            "ogUrl": "https://github.com/a16z/awesome-farcaster",
            "ogType": "object",
            "favicon": "https://github.githubassets.com/favicons/favicon.svg",
            "ogImage": [
              {
                "alt": "A collection of awesome Farcaster links including clients, tools, and more. - a16z/awesome-farcaster",
                "url": "https://opengraph.githubassets.com/bd1b4a2396b9fdb64816e99cbccc743e055a27d526be76918326c18f0a53d18e/a16z/awesome-farcaster",
                "width": "1200",
                "height": "600"
              }
            ],
            "ogTitle": "GitHub - a16z/awesome-farcaster: A collection of awesome Farcaster links including clients, tools, and more.",
            "ogLocale": "en",
            "ogSiteName": "GitHub",
            "ogDescription": "A collection of awesome Farcaster links including clients, tools, and more. - a16z/awesome-farcaster"
          }
        }
      }
    ],
    "enrichment_status": "SUCCESS"
  },
  {
    "cast_hash": "0x871d471c",
    "url": "https://warpcast.com/dwr.eth/0x871d471c",
    "author_username": "dwr.eth",
    "show_date": "2024-02-07",
    "show_title": "GM Farcaster ep58, Feb 7, 2024",
    "source_episode_id": "OcxOrKNO6ak",
    "author_fid": 3,
    "author_pfp": "https://imagedelivery.net/BXluQx4ige9GuW0Ia56BHw/bc698287-5adc-4cc5-a503-de16963ed900/original",
    "cast_date": "2024-02-02T18:21:52.000Z",
    "text": "are you ready for farcon, anon?\n\nhttps://warpcast.com/robrecht.eth/0x293bd7a9",
    "embeds": [
      {
        "cast_id": {
          "fid": 2417,
          "hash": "0x293bd7a91e59f0955fcd2a6136a4a7d9d775f957"
        },
        "cast": {}
      }
    ],
    "enrichment_status": "SUCCESS"
  },
  {
    "cast_hash": "0xd2964f0a",
    "url": "https://warpcast.com/ghostlinkz.eth/0xd2964f0a",
    "author_username": "ghostlinkz.eth",
    "show_date": "2024-02-07",
    "show_title": "GM Farcaster ep58, Feb 7, 2024",
    "source_episode_id": "OcxOrKNO6ak",
    "author_fid": 3115,
    "author_pfp": "https://imagedelivery.net/BXluQx4ige9GuW0Ia56BHw/80cb3761-6951-49a1-71c5-be9da3b93400/original",
    "cast_date": "2024-02-04T23:40:17.000Z",
    "text": "This week's most active users on Farcaster:\n\n1. @guapolocal.eth \n2. @wake \n3. @dwr.eth \n4. @jesse.base.eth \n5. @greyseymour \n\nhttps://outcasters.xyz/snapshot-030",
    "embeds": [
      {
        "url": "https://i.imgur.com/K5XqSRx.jpg",
        "metadata": {
          "content_type": "image/jpeg",
          "content_length": 260140,
          "_status": "RESOLVED",
          "image": {
            "width_px": 566,
            "height_px": 410
          }
        }
      },
      {
        "url": "https://outcasters.xyz/snapshot-030",
        "metadata": {
          "content_type": "text/html;charset=utf-8",
          "content_length": null,
          "_status": "RESOLVED",
          "html": {
            "ogDate": "2024-02-04T23:35:37.443Z",
            "favicon": "https://storage.googleapis.com/papyrus_images/ac0da8f89302b85c218f6da2e7632d79",
            "ogImage": [
              {
                "alt": "Snapshot 030",
                "url": "https://storage.googleapis.com/papyrus_images/83aae50d19c6536c3b99aa1725860558.png",
                "type": "png",
                "width": "1024",
                "height": "512"
              }
            ],
            "ogTitle": "Snapshot 030",
            "ogLocale": "en",
            "ogDescription": "This week's snapshot is curated by my favorite Awkquarian on Farcaster, who has been actively involved in the Web3 space since 2018. Born in 1997, Rakshita considers herself a true digital native. Her on-chain journey has led her to various communities...",
            "fcFrame": {
              "button": {
                "title": "Read",
                "action": {
                  "url": "https://paragraph.com/@outcasters/snapshot-030?frame=true",
                  "name": "Paragraph",
                  "type": "launch_frame",
                  "splashImageUrl": "https://paragraph.com/branding/v2/logomark.png",
                  "splashBackgroundColor": "#26251A"
                }
              },
              "version": "next",
              "imageUrl": "https://paragraph.com/api/og?title=Snapshot%20030&blogName=Outcasters&blogImageUrl=https%3A%2F%2Fstorage.googleapis.com%2Fpapyrus_images%2Fac0da8f89302b85c218f6da2e7632d79&coverPhotoUrl=https%3A%2F%2Fstorage.googleapis.com%2Fpapyrus_images%2F83aae50d19c6536c3b99aa1725860558.png&size=2048&publishedDate=1707089737443"
            }
          },
          "frame": {
            "version": "next",
            "title": "Read",
            "image": "https://paragraph.com/api/og?title=Snapshot%20030&blogName=Outcasters&blogImageUrl=https%3A%2F%2Fstorage.googleapis.com%2Fpapyrus_images%2Fac0da8f89302b85c218f6da2e7632d79&coverPhotoUrl=https%3A%2F%2Fstorage.googleapis.com%2Fpapyrus_images%2F83aae50d19c6536c3b99aa1725860558.png&size=2048&publishedDate=1707089737443",
            "frames_url": "https://outcasters.xyz/snapshot-030"
          }
        }
      }
    ],
    "enrichment_status": "SUCCESS"
  },
  {
    "cast_hash": "0xc042e2d1",
    "url": "https://warpcast.com/ghostlinkz.eth/0xc042e2d1",
    "author_username": "ghostlinkz.eth",
    "show_date": "2024-02-07",
    "show_title": "GM Farcaster ep58, Feb 7, 2024",
    "source_episode_id": "OcxOrKNO6ak",
    "author_fid": 3115,
    "author_pfp": "https://imagedelivery.net/BXluQx4ige9GuW0Ia56BHw/80cb3761-6951-49a1-71c5-be9da3b93400/original",
    "cast_date": "2024-02-04T23:55:04.000Z",
    "text": "This week's most active channels on Farcaster:\n\n1. /degen \n2. /frames \n3. /farcaster \n4. /base \n5. /indonesia\n\nhttps://outcasters.xyz/snapshot-030",
    "embeds": [
      {
        "url": "https://i.imgur.com/XRHKDOZ.jpg",
        "metadata": {
          "content_type": "image/jpeg",
          "content_length": 257692,
          "_status": "RESOLVED",
          "image": {
            "width_px": 566,
            "height_px": 410
          }
        }
      },
      {
        "url": "https://outcasters.xyz/snapshot-030",
        "metadata": {
          "content_type": "text/html;charset=utf-8",
          "content_length": null,
          "_status": "RESOLVED",
          "html": {
            "ogDate": "2024-02-04T23:35:37.443Z",
            "favicon": "https://storage.googleapis.com/papyrus_images/ac0da8f89302b85c218f6da2e7632d79",
            "ogImage": [
              {
                "alt": "Snapshot 030",
                "url": "https://storage.googleapis.com/papyrus_images/83aae50d19c6536c3b99aa1725860558.png",
                "type": "png",
                "width": "1024",
                "height": "512"
              }
            ],
            "ogTitle": "Snapshot 030",
            "ogLocale": "en",
            "ogDescription": "This week's snapshot is curated by my favorite Awkquarian on Farcaster, who has been actively involved in the Web3 space since 2018. Born in 1997, Rakshita considers herself a true digital native. Her on-chain journey has led her to various communities...",
            "fcFrame": {
              "button": {
                "title": "Read",
                "action": {
                  "url": "https://paragraph.com/@outcasters/snapshot-030?frame=true",
                  "name": "Paragraph",
                  "type": "launch_frame",
                  "splashImageUrl": "https://paragraph.com/branding/v2/logomark.png",
                  "splashBackgroundColor": "#26251A"
                }
              },
              "version": "next",
              "imageUrl": "https://paragraph.com/api/og?title=Snapshot%20030&blogName=Outcasters&blogImageUrl=https%3A%2F%2Fstorage.googleapis.com%2Fpapyrus_images%2Fac0da8f89302b85c218f6da2e7632d79&coverPhotoUrl=https%3A%2F%2Fstorage.googleapis.com%2Fpapyrus_images%2F83aae50d19c6536c3b99aa1725860558.png&size=2048&publishedDate=1707089737443"
            }
          },
          "frame": {
            "version": "next",
            "title": "Read",
            "image": "https://paragraph.com/api/og?title=Snapshot%20030&blogName=Outcasters&blogImageUrl=https%3A%2F%2Fstorage.googleapis.com%2Fpapyrus_images%2Fac0da8f89302b85c218f6da2e7632d79&coverPhotoUrl=https%3A%2F%2Fstorage.googleapis.com%2Fpapyrus_images%2F83aae50d19c6536c3b99aa1725860558.png&size=2048&publishedDate=1707089737443",
            "frames_url": "https://outcasters.xyz/snapshot-030"
          }
        }
      }
    ],
    "enrichment_status": "SUCCESS"
  },
  {
    "cast_hash": "0x9c3c6b6d",
    "url": "https://warpcast.com/cameron/0x9c3c6b6d",
    "author_username": "cameron",
    "show_date": "2024-02-07",
    "show_title": "GM Farcaster ep58, Feb 7, 2024",
    "source_episode_id": "OcxOrKNO6ak",
    "author_fid": 617,
    "author_pfp": "https://imagedelivery.net/BXluQx4ige9GuW0Ia56BHw/ac4e8cdc-f317-4711-d742-bb59c4651d00/original",
    "cast_date": "2024-02-03T16:06:59.000Z",
    "text": "Real talk:\n\nWhat do we think this levels out at steady state?\n\nHow does this change Farcaster? \n\nHow does this change how you think of Farcaster as a builder?",
    "embeds": [
      {
        "cast_id": {
          "fid": 3,
          "hash": "0xc352e461780c3d18e2e1f7228cbf3648b04c3aaf"
        },
        "cast": {
          "object": "cast_embedded",
          "hash": "0xc352e461780c3d18e2e1f7228cbf3648b04c3aaf",
          "author": {
            "object": "user_dehydrated",
            "fid": 3,
            "username": "dwr.eth",
            "display_name": "Dan Romero",
            "pfp_url": "https://imagedelivery.net/BXluQx4ige9GuW0Ia56BHw/bc698287-5adc-4cc5-a503-de16963ed900/original",
            "custody_address": "0x6b0bda3f2ffed5efc83fa8c024acff1dd45793f1"
          },
          "app": {
            "object": "user_dehydrated",
            "fid": 9152,
            "username": "warpcast",
            "display_name": "Warpcast",
            "pfp_url": "https://i.imgur.com/3d6fFAI.png",
            "custody_address": "0x02ef790dd7993a35fd847c053eddae940d055596"
          },
          "thread_hash": "0xc352e461780c3d18e2e1f7228cbf3648b04c3aaf",
          "parent_hash": null,
          "parent_url": "chain://eip155:7777777/erc721:0x10a77f29a6bbeae936f3f27cd60546072dae4e41",
          "root_parent_url": "chain://eip155:7777777/erc721:0x10a77f29a6bbeae936f3f27cd60546072dae4e41",
          "parent_author": {
            "fid": null
          },
          "text": "7th consecutive record DAU day yesterday!\n\nFirst time over 30K!",
          "timestamp": "2024-02-03T15:40:41.000Z",
          "embeds": [
            {
              "url": "https://i.imgur.com/KlrBuZ5.png",
              "metadata": {
                "content_type": "image/png",
                "content_length": 16986,
                "_status": "RESOLVED",
                "image": {
                  "width_px": 302,
                  "height_px": 256
                }
              }
            }
          ],
          "channel": {
            "object": "channel_dehydrated",
            "id": "warpcast",
            "name": "Warpcast",
            "image_url": "https://ipfs.decentralized-content.com/ipfs/bafkreifezhnp5wzgabkdbkb6d65oix4r5axibupv45r7ifxphl4d6qqnry"
          }
        }
      }
    ],
    "enrichment_status": "SUCCESS"
  },
  {
    "cast_hash": "0x92485e36",
    "url": "https://warpcast.com/nonlinear.eth/0x92485e36",
    "author_username": "nonlinear.eth",
    "show_date": "2024-02-07",
    "show_title": "GM Farcaster ep58, Feb 7, 2024",
    "source_episode_id": "OcxOrKNO6ak",
    "author_fid": 576,
    "author_pfp": "https://i.seadn.io/gae/oeyOFjLzIVCMec49KdmBp24ZHL82XXqLLDlLRuvUR8InycSpmf9ZtSCfN69lgojeOoucD7fU9cjxAt4raFBTTgSo34gD5lSZ83Klb1k?w=500&auto=format",
    "cast_date": "2024-02-06T14:34:24.000Z",
    "text": "If you are rocking a FID above 1k plz don't @ me or share your opinion on my wall. I don't care what you have to say. Reality is you need to Work harder, move out of your moms basement, stack eth/sol, buy a few real PFP then share your opinion.",
    "embeds": [
      {
        "cast_id": {
          "fid": 9410,
          "hash": "0x1841e8731e809467a410c0455ceff268f817c029"
        },
        "cast": {
          "object": "cast_embedded",
          "hash": "0x1841e8731e809467a410c0455ceff268f817c029",
          "author": {
            "object": "user_dehydrated",
            "fid": 9410,
            "username": "gmoney.eth",
            "display_name": "gmoney",
            "pfp_url": "https://i.imgur.com/Trq88ar.png",
            "custody_address": "0x4444489f7568dd2f158dea24d6e925b85b4589eb"
          },
          "app": {
            "object": "user_dehydrated",
            "fid": 9152,
            "username": "warpcast",
            "display_name": "Warpcast",
            "pfp_url": "https://i.imgur.com/3d6fFAI.png",
            "custody_address": "0x02ef790dd7993a35fd847c053eddae940d055596"
          },
          "thread_hash": "0x1841e8731e809467a410c0455ceff268f817c029",
          "parent_hash": null,
          "parent_url": null,
          "root_parent_url": null,
          "parent_author": {
            "fid": null
          },
          "text": "If you are rocking a FID above 10k plz don't @ me or share your opinion on my wall. I don't care what you have to say. Reality is you need to Work harder, move out of your moms basement, stack eth/sol, buy a few real PFP then share your opinion.",
          "timestamp": "2024-02-06T11:15:05.000Z",
          "embeds": [],
          "channel": null
        }
      }
    ],
    "enrichment_status": "SUCCESS"
  },
  {
    "cast_hash": "0xd81a48a5",
    "url": "https://warpcast.com/ahn.eth/0xd81a48a5",
    "author_username": "ahn.eth",
    "show_date": "2024-02-07",
    "show_title": "GM Farcaster ep58, Feb 7, 2024",
    "source_episode_id": "OcxOrKNO6ak",
    "author_fid": 8004,
    "author_pfp": "https://imagedelivery.net/BXluQx4ige9GuW0Ia56BHw/cca05e9f-4f52-45c9-ebdb-c60ec8f93d00/rectcrop3",
    "cast_date": "2024-02-06T14:14:53.000Z",
    "text": "daily affirmation: i am a qdau no matter what anyone else says 🫂",
    "embeds": [
      {
        "url": "https://i.imgur.com/tsrxkPA.jpg",
        "metadata": {
          "content_type": "image/jpeg",
          "content_length": 64294,
          "_status": "RESOLVED",
          "image": {
            "width_px": 500,
            "height_px": 500
          }
        }
      }
    ],
    "enrichment_status": "SUCCESS"
  },
  {
    "cast_hash": "0x39c05a79",
    "url": "https://warpcast.com/goose/0x39c05a79",
    "author_username": "goose",
    "show_date": "2024-02-07",
    "show_title": "GM Farcaster ep58, Feb 7, 2024",
    "source_episode_id": "OcxOrKNO6ak",
    "author_fid": 225,
    "author_pfp": "https://imagedelivery.net/BXluQx4ige9GuW0Ia56BHw/cd82f5e9-389e-4e79-aba0-f2426021c700/rectcrop3",
    "cast_date": "2024-02-06T22:43:18.000Z",
    "text": "please do not tell my wife 😅",
    "embeds": [
      {
        "url": "https://i.imgur.com/HqYeWth.png",
        "metadata": {
          "content_type": "image/png",
          "content_length": 73825,
          "_status": "RESOLVED",
          "image": {
            "width_px": 1266,
            "height_px": 484
          }
        }
      }
    ],
    "enrichment_status": "SUCCESS"
  }
]