[
  {
    "cast_hash": "0x92f8cd55",
    "url": "https://warpcast.com/dwr.eth/0x92f8cd55",
    "author_username": "dwr.eth",
    "show_date": "2024-01-04",
    "show_title": "GM Farcaster ep23 Nov 10, 2023",
    "source_episode_id": "N0s6TwJ_IWE",
    "author_fid": 3,
    "author_pfp": "https://imagedelivery.net/BXluQx4ige9GuW0Ia56BHw/bc698287-5adc-4cc5-a503-de16963ed900/original",
    "cast_date": "2023-11-08T16:11:38.000Z",
    "text": "Little known fact: the hated W in the Warpcast logo stands for wowow",
    "embeds": [
      {
        "url": "https://i.imgur.com/OYHtdT6.png",
        "metadata": {
          "content_type": "image/png",
          "content_length": 186071,
          "_status": "RESOLVED",
          "image": {
            "width_px": 1024,
            "height_px": 1024
          }
        }
      }
    ],
    "enrichment_status": "SUCCESS"
  },
  {
    "cast_hash": "0x73255a32",
    "url": "https://warpcast.com/sheldon/0x73255a32",
    "author_username": "sheldon",
    "show_date": "2024-01-04",
    "show_title": "GM Farcaster ep23 Nov 10, 2023",
    "source_episode_id": "N0s6TwJ_IWE",
    "author_fid": 7960,
    "author_pfp": "https://i.seadn.io/gcs/files/d3b632e170e19390fe67abb5fb269fff.jpg?w=500&auto=format",
    "cast_date": "2023-11-08T19:11:03.000Z",
    "text": "Wanted to share this with my fellow gentleman and gentlelady meme connoisseurs 😂\n\nSource: https://warpcast.com/sheldon/0x54cf741e",
    "embeds": [
      {
        "url": "https://i.imgur.com/qLBuWLm.jpg",
        "metadata": {
          "content_type": "image/jpeg",
          "content_length": 279862,
          "_status": "RESOLVED",
          "image": {
            "width_px": 1229,
            "height_px": 685
          }
        }
      },
      {
        "url": "https://warpcast.com/sheldon/0x54cf741e",
        "metadata": {
          "content_type": "text/html;charset=utf-8",
          "content_length": null,
          "_status": "RESOLVED",
          "html": {
            "ogUrl": "https://warpcast.com/sheldon/0x54cf741e",
            "ogType": "article",
            "favicon": "/favicon.png",
            "ogImage": [
              {
                "url": "https://client.warpcast.com/v2/og-image?castHash=0x54cf741ed38828ba3a19c7d03416ea01abac08f8",
                "width": "1200",
                "height": "630"
              }
            ],
            "ogTitle": "Sheldon Trotman on Warpcast",
            "ogLocale": "en",
            "ogSiteName": "Warpcast",
            "ogDescription": "I’m sorry I couldn’t help myself 😂please don’t mark me as spam 🫣👀 https://i.imgur.com/8Hj2Fkb.jpg"
          }
        }
      }
    ],
    "enrichment_status": "SUCCESS"
  },
  {
    "cast_hash": "0x9a8010a3",
    "url": "https://warpcast.com/dwr.eth/0x9a8010a3",
    "author_username": "dwr.eth",
    "show_date": "2024-01-04",
    "show_title": "GM Farcaster ep23 Nov 10, 2023",
    "source_episode_id": "N0s6TwJ_IWE",
    "author_fid": 3,
    "author_pfp": "https://imagedelivery.net/BXluQx4ige9GuW0Ia56BHw/bc698287-5adc-4cc5-a503-de16963ed900/original",
    "cast_date": "2023-11-08T17:37:40.000Z",
    "text": "ω○ω○ω",
    "embeds": [],
    "enrichment_status": "SUCCESS"
  },
  {
    "cast_hash": "0x602909ae",
    "url": "https://warpcast.com/philcockfield.eth/0x602909ae",
    "author_username": "philcockfield.eth",
    "show_date": "2024-01-04",
    "show_title": "GM Farcaster ep23 Nov 10, 2023",
    "source_episode_id": "N0s6TwJ_IWE",
    "author_fid": 12567,
    "author_pfp": "https://i.seadn.io/gcs/files/3e92955b4b56afa756514e6a29ff55ad.jpg?w=500&auto=format",
    "cast_date": "2023-11-09T04:47:06.000Z",
    "text": "(just minted)...wowow!",
    "embeds": [
      {
        "url": "https://zora.co/collect/zora:0xedc465e25c99afabee4ec310e892571341e2f66b/1?referrer=0x1DA44DC5bD3ccAd7c9DE272a58B5507F5bc251fA",
        "metadata": {
          "content_type": "text/html;charset=utf-8",
          "content_length": null,
          "_status": "RESOLVED",
          "html": {
            "ogUrl": "https://zora.co/collect/zora:0xedc465e25c99afabee4ec310e892571341e2f66b/1",
            "favicon": "https://zora.co/favicon/favicon.png",
            "ogImage": [
              {
                "url": "https://zora.co/api/og-image/post/zora:0xedc465e25c99afabee4ec310e892571341e2f66b/1?v=2&mints=7"
              }
            ],
            "ogTitle": "Low Effort Reply Guy",
            "ogLocale": "en",
            "ogSiteName": "Zora",
            "ogDescription": "Web3 enthusiast – follow 4 follow – I love crypto!",
            "fcFrame": {
              "button": {
                "title": "Buy",
                "action": {
                  "url": "https://zora.co/collect/zora:0xedc465e25c99afabee4ec310e892571341e2f66b/1/frame-v2",
                  "name": "Buy",
                  "type": "launch_frame",
                  "splashImageUrl": "https://zora.co/assets/logo.png",
                  "splashBackgroundColor": "#ffffff"
                }
              },
              "version": "next",
              "imageUrl": "https://zora.co/api/og-image/post/zora:0xedc465e25c99afabee4ec310e892571341e2f66b/1?v=2&mints=7&crop=farcaster"
            }
          },
          "frame": {
            "version": "next",
            "title": "Buy",
            "image": "https://zora.co/api/og-image/post/zora:0xedc465e25c99afabee4ec310e892571341e2f66b/1?v=2&mints=7&crop=farcaster",
            "frames_url": "https://zora.co/collect/zora:0xedc465e25c99afabee4ec310e892571341e2f66b/1?referrer=0x1DA44DC5bD3ccAd7c9DE272a58B5507F5bc251fA"
          }
        }
      }
    ],
    "enrichment_status": "SUCCESS"
  },
  {
    "cast_hash": "0x2b1514f0",
    "url": "https://warpcast.com/obxium/0x2b1514f0",
    "author_username": "obxium",
    "show_date": "2024-01-04",
    "show_title": "GM Farcaster ep23 Nov 10, 2023",
    "source_episode_id": "N0s6TwJ_IWE",
    "enrichment_status": "FAILED",
    "enrichment_status_code": 404
  },
  {
    "cast_hash": "0xafc204d8",
    "url": "https://warpcast.com/obxium/0xafc204d8",
    "author_username": "obxium",
    "show_date": "2024-01-04",
    "show_title": "GM Farcaster ep23 Nov 10, 2023",
    "source_episode_id": "N0s6TwJ_IWE",
    "enrichment_status": "FAILED",
    "enrichment_status_code": 404
  },
  {
    "cast_hash": "0x3018354b",
    "url": "https://warpcast.com/greg/0x3018354b",
    "author_username": "greg",
    "show_date": "2024-01-04",
    "show_title": "GM Farcaster ep23 Nov 10, 2023",
    "source_episode_id": "N0s6TwJ_IWE",
    "author_fid": 347,
    "author_pfp": "https://i.seadn.io/gae/YsASemS2qwPJK2yI9fmN8HX1-DeIDy9EQxX4KsRk9rkniwn9A7xUyMu_vKR75Oxrs8QAKfIjqdmf6Aw9A9fsehJHWSz2LiNpnV_TPQ?w=500&auto=format",
    "cast_date": "2023-11-09T16:38:45.000Z",
    "text": "sorry boomers but wowow isn't that funny",
    "embeds": [],
    "enrichment_status": "SUCCESS"
  },
  {
    "cast_hash": "0xc65e339b",
    "url": "https://warpcast.com/linda/0xc65e339b",
    "author_username": "linda",
    "show_date": "2024-01-04",
    "show_title": "GM Farcaster ep23 Nov 10, 2023",
    "source_episode_id": "N0s6TwJ_IWE",
    "author_fid": 12,
    "author_pfp": "https://imagedelivery.net/BXluQx4ige9GuW0Ia56BHw/6aa18817-6238-4b25-086f-1edd0c438f00/original",
    "cast_date": "2023-11-10T02:47:05.000Z",
    "text": "New wowow category on @bountycaster",
    "embeds": [
      {
        "url": "https://i.imgur.com/hrW8g1K.png",
        "metadata": {
          "content_type": "image/png",
          "content_length": 227742,
          "_status": "RESOLVED",
          "image": {
            "width_px": 1468,
            "height_px": 1580
          }
        }
      }
    ],
    "enrichment_status": "SUCCESS"
  },
  {
    "cast_hash": "0x3ec05cb9",
    "url": "https://warpcast.com/sealaunch/0x3ec05cb9",
    "author_username": "sealaunch",
    "show_date": "2024-01-04",
    "show_title": "GM Farcaster ep23 Nov 10, 2023",
    "source_episode_id": "N0s6TwJ_IWE",
    "author_fid": 11032,
    "author_pfp": "https://i.imgur.com/JJhA7OA.jpg",
    "cast_date": "2023-11-08T17:54:14.000Z",
    "text": "wowow @dwr.eth",
    "embeds": [
      {
        "url": "https://i.imgur.com/qMDARNT.png",
        "metadata": {
          "content_type": "image/png",
          "content_length": 174361,
          "_status": "RESOLVED",
          "image": {
            "width_px": 2522,
            "height_px": 1396
          }
        }
      }
    ],
    "enrichment_status": "SUCCESS"
  },
  {
    "cast_hash": "0x3048290c",
    "url": "https://warpcast.com/emre/0x3048290c",
    "author_username": "emre",
    "show_date": "2024-01-04",
    "show_title": "GM Farcaster ep23 Nov 10, 2023",
    "source_episode_id": "N0s6TwJ_IWE",
    "author_fid": 788,
    "author_pfp": "https://imagedelivery.net/BXluQx4ige9GuW0Ia56BHw/9580e82b-6813-4768-f83b-5c24569c3300/original",
    "cast_date": "2023-11-08T20:30:15.000Z",
    "text": "most important chart of the day\n\nwowows per day",
    "embeds": [
      {
        "url": "https://i.imgur.com/WDIYq7F.png",
        "metadata": {
          "content_type": "image/png",
          "content_length": 76357,
          "_status": "RESOLVED",
          "image": {
            "width_px": 2058,
            "height_px": 670
          }
        }
      }
    ],
    "enrichment_status": "SUCCESS"
  },
  {
    "cast_hash": "0xc7c6dd6a",
    "url": "https://warpcast.com/dwr.eth/0xc7c6dd6a",
    "author_username": "dwr.eth",
    "show_date": "2024-01-04",
    "show_title": "GM Farcaster ep23 Nov 10, 2023",
    "source_episode_id": "N0s6TwJ_IWE",
    "author_fid": 3,
    "author_pfp": "https://imagedelivery.net/BXluQx4ige9GuW0Ia56BHw/bc698287-5adc-4cc5-a503-de16963ed900/original",
    "cast_date": "2023-11-09T16:37:48.000Z",
    "text": "More aggressive, proactive spam filtering would have prevented wowow meta.\n\nWhat if spam is an untapped meme energy source?",
    "embeds": [],
    "enrichment_status": "SUCCESS"
  },
  {
    "cast_hash": "0x57cc2d7f",
    "url": "https://warpcast.com/dwr.eth/0x57cc2d7f",
    "author_username": "dwr.eth",
    "show_date": "2024-01-04",
    "show_title": "GM Farcaster ep23 Nov 10, 2023",
    "source_episode_id": "N0s6TwJ_IWE",
    "author_fid": 3,
    "author_pfp": "https://imagedelivery.net/BXluQx4ige9GuW0Ia56BHw/bc698287-5adc-4cc5-a503-de16963ed900/original",
    "cast_date": "2023-11-09T16:33:46.000Z",
    "text": "",
    "embeds": [
      {
        "url": "https://i.imgur.com/GXl82pk.png",
        "metadata": {
          "content_type": "image/png",
          "content_length": 40707,
          "_status": "RESOLVED",
          "image": {
            "width_px": 532,
            "height_px": 318
          }
        }
      }
    ],
    "enrichment_status": "SUCCESS"
  },
  {
    "cast_hash": "0x69b74541",
    "url": "https://warpcast.com/dwr.eth/0x69b74541",
    "author_username": "dwr.eth",
    "show_date": "2024-01-04",
    "show_title": "GM Farcaster ep23 Nov 10, 2023",
    "source_episode_id": "N0s6TwJ_IWE",
    "author_fid": 3,
    "author_pfp": "https://imagedelivery.net/BXluQx4ige9GuW0Ia56BHw/bc698287-5adc-4cc5-a503-de16963ed900/original",
    "cast_date": "2023-11-08T22:02:26.000Z",
    "text": "re: boosts — just a test of the emergency broadcast system\n\nWill be done in 15 minutes or so.",
    "embeds": [],
    "enrichment_status": "SUCCESS"
  },
  {
    "cast_hash": "0xa2bac5e6",
    "url": "https://warpcast.com/0xen/0xa2bac5e6",
    "author_username": "0xen",
    "show_date": "2024-01-04",
    "show_title": "GM Farcaster ep23 Nov 10, 2023",
    "source_episode_id": "N0s6TwJ_IWE",
    "enrichment_status": "FAILED",
    "enrichment_status_code": 404
  },
  {
    "cast_hash": "0x3ac0b67d",
    "url": "https://warpcast.com/adrienne/0x3ac0b67d",
    "author_username": "adrienne",
    "show_date": "2024-01-04",
    "show_title": "GM Farcaster ep23 Nov 10, 2023",
    "source_episode_id": "N0s6TwJ_IWE",
    "author_fid": 5818,
    "author_pfp": "https://tba-mobile.mypinata.cloud/ipfs/QmUde33nkJWk9gGWQXHLhSrjBfGjDosrH9dKWSpLURkZZC?pinataGatewayToken=PMz6RFTDuk-300OttNnb_U0PSKbbXQdzLmUqdiEq7lesXcsVK8TK7S5GoOtxRGl2",
    "cast_date": "2023-11-08T21:48:57.000Z",
    "text": "Warps were last week. Wowow was so yesterday. I’m all about boosts today.",
    "embeds": [],
    "enrichment_status": "SUCCESS"
  },
  {
    "cast_hash": "0x8c1ed39a",
    "url": "https://warpcast.com/dwr.eth/0x8c1ed39a",
    "author_username": "dwr.eth",
    "show_date": "2024-01-04",
    "show_title": "GM Farcaster ep23 Nov 10, 2023",
    "source_episode_id": "N0s6TwJ_IWE",
    "author_fid": 3,
    "author_pfp": "https://imagedelivery.net/BXluQx4ige9GuW0Ia56BHw/bc698287-5adc-4cc5-a503-de16963ed900/original",
    "cast_date": "2023-11-08T22:10:56.000Z",
    "text": "gm",
    "embeds": [
      {
        "url": "https://i.imgur.com/tCeYJLp.jpg",
        "metadata": {
          "content_type": "image/jpeg",
          "content_length": 92308,
          "_status": "RESOLVED",
          "image": {
            "width_px": 500,
            "height_px": 659
          }
        }
      }
    ],
    "enrichment_status": "SUCCESS"
  },
  {
    "cast_hash": "0xc71cfdc1",
    "url": "https://warpcast.com/dwr.eth/0xc71cfdc1",
    "author_username": "dwr.eth",
    "show_date": "2024-01-04",
    "show_title": "GM Farcaster ep23 Nov 10, 2023",
    "source_episode_id": "N0s6TwJ_IWE",
    "author_fid": 3,
    "author_pfp": "https://imagedelivery.net/BXluQx4ige9GuW0Ia56BHw/bc698287-5adc-4cc5-a503-de16963ed900/original",
    "cast_date": "2023-11-08T22:24:16.000Z",
    "text": "just finished a delicious snack",
    "embeds": [
      {
        "url": "https://i.imgur.com/zvNGs7e.jpg",
        "metadata": {
          "content_type": "image/jpeg",
          "content_length": 256667,
          "_status": "RESOLVED",
          "image": {
            "width_px": 1200,
            "height_px": 1200
          }
        }
      }
    ],
    "enrichment_status": "SUCCESS"
  },
  {
    "cast_hash": "0x71a6ebcc",
    "url": "https://warpcast.com/fun/0x71a6ebcc",
    "author_username": "fun",
    "show_date": "2024-01-04",
    "show_title": "GM Farcaster ep23 Nov 10, 2023",
    "source_episode_id": "N0s6TwJ_IWE",
    "author_fid": 5620,
    "author_pfp": "https://imagedelivery.net/BXluQx4ige9GuW0Ia56BHw/d793c077-f8fc-4bd6-3c4c-d5b03603a400/original",
    "cast_date": "2023-11-09T14:42:34.000Z",
    "text": "gm to the new meta",
    "embeds": [
      {
        "url": "https://i.imgur.com/B9ww0oW.jpg",
        "metadata": {
          "content_type": "image/jpeg",
          "content_length": 575901,
          "_status": "RESOLVED",
          "image": {
            "width_px": 2494,
            "height_px": 1403
          }
        }
      }
    ],
    "enrichment_status": "SUCCESS"
  },
  {
    "cast_hash": "0x49b63812",
    "url": "https://warpcast.com/grin/0x49b63812",
    "author_username": "grin",
    "show_date": "2024-01-04",
    "show_title": "GM Farcaster ep23 Nov 10, 2023",
    "source_episode_id": "N0s6TwJ_IWE",
    "author_fid": 1970,
    "author_pfp": "https://imagedelivery.net/BXluQx4ige9GuW0Ia56BHw/e8d65d0e-42de-4237-1159-128e81c94900/original",
    "cast_date": "2023-11-09T13:58:29.000Z",
    "text": "there are dozens of us, DOZENS!\n\nhttps://warpcast.com/woj.eth/0x113cc199",
    "embeds": [
      {
        "url": "https://i.imgur.com/SlBfsu8.png",
        "metadata": {
          "content_type": "image/png",
          "content_length": 139096,
          "_status": "RESOLVED",
          "image": {
            "width_px": 698,
            "height_px": 883
          }
        }
      },
      {
        "url": "https://warpcast.com/woj.eth/0x113cc199",
        "metadata": {
          "content_type": "text/html;charset=utf-8",
          "content_length": null,
          "_status": "RESOLVED",
          "html": {
            "ogUrl": "https://warpcast.com/woj.eth/0x113cc199",
            "ogType": "article",
            "favicon": "/favicon.png",
            "ogImage": [
              {
                "url": "https://client.warpcast.com/v2/og-image?castHash=0x113cc199e8a585248b54d4003bd2f27c9638bfc9",
                "width": "1200",
                "height": "630"
              }
            ],
            "ogTitle": "​woj on Warpcast",
            "ogLocale": "en",
            "ogSiteName": "Warpcast",
            "ogDescription": "im happy to announce that the new meta has officially started https://i.imgur.com/ux9EsBo.png"
          }
        }
      }
    ],
    "enrichment_status": "SUCCESS"
  },
  {
    "cast_hash": "0x264ffeee",
    "url": "https://warpcast.com/cameron/0x264ffeee",
    "author_username": "cameron",
    "show_date": "2024-01-04",
    "show_title": "GM Farcaster ep23 Nov 10, 2023",
    "source_episode_id": "N0s6TwJ_IWE",
    "author_fid": 617,
    "author_pfp": "https://imagedelivery.net/BXluQx4ige9GuW0Ia56BHw/ac4e8cdc-f317-4711-d742-bb59c4651d00/original",
    "cast_date": "2023-11-08T18:15:24.000Z",
    "text": "On the 8th Day of \n\n🍁Farcaster Fall🍁\n\nmy true love gave to me…\n\nA mint by @cybershakti 🥲\n\nWe got a sick one today, folks 🫡\n\nhttps://zora.co/collect/zora:0x7603103f6df23d3f2d1722865965511df2252437/premint-1",
    "embeds": [
      {
        "url": "https://i.imgur.com/URGgEKe.gif",
        "metadata": {
          "content_type": "image/gif",
          "content_length": 5327063,
          "_status": "RESOLVED",
          "image": {
            "width_px": 600,
            "height_px": 338
          }
        }
      },
      {
        "url": "https://zora.co/collect/zora:0x7603103f6df23d3f2d1722865965511df2252437/premint-1?referrer=0xBe3FC886e104904935cfC5f4F32F4CCec06CbA79",
        "metadata": {
          "_status": "PENDING"
        }
      }
    ],
    "enrichment_status": "SUCCESS"
  },
  {
    "cast_hash": "0xda2e48ee",
    "url": "https://warpcast.com/cameron/0xda2e48ee",
    "author_username": "cameron",
    "show_date": "2024-01-04",
    "show_title": "GM Farcaster ep23 Nov 10, 2023",
    "source_episode_id": "N0s6TwJ_IWE",
    "author_fid": 617,
    "author_pfp": "https://imagedelivery.net/BXluQx4ige9GuW0Ia56BHw/ac4e8cdc-f317-4711-d742-bb59c4651d00/original",
    "cast_date": "2023-11-09T12:33:00.000Z",
    "text": "Running back a classic feel here on Day 9 of 🍁Farcaster Fall🍁\n\nHuge thank you to @mxvoid for the submission!\n\nSpread the word - you still have time to join the fun 🫡\n\nhttps://zora.co/collect/zora:0x53cae7c754240a908860a57e408a1b3dc900f20c/2",
    "embeds": [
      {
        "url": "https://zora.co/collect/zora:0x53cae7c754240a908860a57e408a1b3dc900f20c/2?referrer=0xBe3FC886e104904935cfC5f4F32F4CCec06CbA79",
        "metadata": {
          "_status": "PENDING"
        }
      }
    ],
    "enrichment_status": "SUCCESS"
  },
  {
    "cast_hash": "0xa3e74283",
    "url": "https://warpcast.com/cameron/0xa3e74283",
    "author_username": "cameron",
    "show_date": "2024-01-04",
    "show_title": "GM Farcaster ep23 Nov 10, 2023",
    "source_episode_id": "N0s6TwJ_IWE",
    "author_fid": 617,
    "author_pfp": "https://imagedelivery.net/BXluQx4ige9GuW0Ia56BHw/ac4e8cdc-f317-4711-d742-bb59c4651d00/original",
    "cast_date": "2023-11-10T12:13:20.000Z",
    "text": "Day TEN of 🍁Farcaster Fall🍁 brings us to the Blue Ridge Parkway where @rileybeans helps us take a breath and reflect on the season 🥲\n\nWe’ve got such a cool community - mint to support right here!\n\nhttps://zora.co/collect/zora:0xe1b426ba781dfa8748400087d1e1910d8a8ce3aa/2",
    "embeds": [
      {
        "url": "https://i.imgur.com/I0vAYqB.gif",
        "metadata": {
          "content_type": "image/gif",
          "content_length": 7380787,
          "_status": "RESOLVED",
          "image": {
            "width_px": 600,
            "height_px": 588
          }
        }
      },
      {
        "url": "https://zora.co/collect/zora:0xe1b426ba781dfa8748400087d1e1910d8a8ce3aa/2?referrer=0xBe3FC886e104904935cfC5f4F32F4CCec06CbA79",
        "metadata": {
          "_status": "PENDING"
        }
      }
    ],
    "enrichment_status": "SUCCESS"
  },
  {
    "cast_hash": "0x0149db35",
    "url": "https://warpcast.com/dwr.eth/0x0149db35",
    "author_username": "dwr.eth",
    "show_date": "2024-01-04",
    "show_title": "GM Farcaster ep23 Nov 10, 2023",
    "source_episode_id": "N0s6TwJ_IWE",
    "author_fid": 3,
    "author_pfp": "https://imagedelivery.net/BXluQx4ige9GuW0Ia56BHw/bc698287-5adc-4cc5-a503-de16963ed900/original",
    "cast_date": "2023-11-08T01:53:54.000Z",
    "text": "What made Farcaster stick as a daily habit you?\n\nAnd if you’re infrequent / inconsistent (but happen to see this), what has you checking the app but not having it be a daily habit?",
    "embeds": [],
    "enrichment_status": "SUCCESS"
  },
  {
    "cast_hash": "0x69b4ae51",
    "url": "https://warpcast.com/adrienne/0x69b4ae51",
    "author_username": "adrienne",
    "show_date": "2024-01-04",
    "show_title": "GM Farcaster ep23 Nov 10, 2023",
    "source_episode_id": "N0s6TwJ_IWE",
    "author_fid": 5818,
    "author_pfp": "https://tba-mobile.mypinata.cloud/ipfs/QmUde33nkJWk9gGWQXHLhSrjBfGjDosrH9dKWSpLURkZZC?pinataGatewayToken=PMz6RFTDuk-300OttNnb_U0PSKbbXQdzLmUqdiEq7lesXcsVK8TK7S5GoOtxRGl2",
    "cast_date": "2023-11-08T01:58:49.000Z",
    "text": "A perfect storm \n\nTiming, I was going through something personal and was probably just open to new habits \n\nTwitter was sucking \n\nI wanted to explore decentralized social, crypto philosophy sucked me in\n\nAnd the playful and engaging energy from early friends 👀 could name dozens but \n@cameron stands out the most",
    "embeds": [],
    "enrichment_status": "SUCCESS"
  },
  {
    "cast_hash": "0x69b4ae51",
    "url": "https://warpcast.com/adrienne/0x69b4ae51",
    "author_username": "adrienne",
    "show_date": "2024-01-04",
    "show_title": "GM Farcaster ep23 Nov 10, 2023",
    "source_episode_id": "N0s6TwJ_IWE",
    "author_fid": 5818,
    "author_pfp": "https://tba-mobile.mypinata.cloud/ipfs/QmUde33nkJWk9gGWQXHLhSrjBfGjDosrH9dKWSpLURkZZC?pinataGatewayToken=PMz6RFTDuk-300OttNnb_U0PSKbbXQdzLmUqdiEq7lesXcsVK8TK7S5GoOtxRGl2",
    "cast_date": "2023-11-08T01:58:49.000Z",
    "text": "A perfect storm \n\nTiming, I was going through something personal and was probably just open to new habits \n\nTwitter was sucking \n\nI wanted to explore decentralized social, crypto philosophy sucked me in\n\nAnd the playful and engaging energy from early friends 👀 could name dozens but \n@cameron stands out the most",
    "embeds": [],
    "enrichment_status": "SUCCESS"
  },
  {
    "cast_hash": "0x88527a06",
    "url": "https://warpcast.com/nounishprof/0x88527a06",
    "author_username": "nounishprof",
    "show_date": "2024-01-04",
    "show_title": "GM Farcaster ep23 Nov 10, 2023",
    "source_episode_id": "N0s6TwJ_IWE",
    "enrichment_status": "FAILED",
    "enrichment_status_code": 404
  },
  {
    "cast_hash": "0xd098e0be",
    "url": "https://warpcast.com/v/0xd098e0be",
    "author_username": "v",
    "show_date": "2024-01-04",
    "show_title": "GM Farcaster ep23 Nov 10, 2023",
    "source_episode_id": "N0s6TwJ_IWE",
    "author_fid": 2,
    "author_pfp": "https://i.seadn.io/gae/sYAr036bd0bRpj7OX6B-F-MqLGznVkK3--DSneL_BT5GX4NZJ3Zu91PgjpD9-xuVJtHq0qirJfPZeMKrahz8Us2Tj_X8qdNPYC-imqs?w=500&auto=format",
    "cast_date": "2023-11-08T22:06:32.000Z",
    "text": "If you cast in channel, it also shows up in home. (as of two weeks ago) \n\nNo need to recast anymore.",
    "embeds": [],
    "enrichment_status": "SUCCESS"
  },
  {
    "cast_hash": "0xb1cab362",
    "url": "https://warpcast.com/v/0xb1cab362",
    "author_username": "v",
    "show_date": "2024-01-04",
    "show_title": "GM Farcaster ep23 Nov 10, 2023",
    "source_episode_id": "N0s6TwJ_IWE",
    "author_fid": 2,
    "author_pfp": "https://i.seadn.io/gae/sYAr036bd0bRpj7OX6B-F-MqLGznVkK3--DSneL_BT5GX4NZJ3Zu91PgjpD9-xuVJtHq0qirJfPZeMKrahz8Us2Tj_X8qdNPYC-imqs?w=500&auto=format",
    "cast_date": "2023-11-09T03:43:38.000Z",
    "text": "actually, there is a minimum threshold - if it gets a few likes and replies, then it will show up, but if it gets nothing it won't get redistributed to your followers.",
    "embeds": [],
    "enrichment_status": "SUCCESS"
  },
  {
    "cast_hash": "0xfb54f18d",
    "url": "https://warpcast.com/nonlinear.eth/0xfb54f18d",
    "author_username": "nonlinear.eth",
    "show_date": "2024-01-04",
    "show_title": "GM Farcaster ep23 Nov 10, 2023",
    "source_episode_id": "N0s6TwJ_IWE",
    "author_fid": 576,
    "author_pfp": "https://i.seadn.io/gae/oeyOFjLzIVCMec49KdmBp24ZHL82XXqLLDlLRuvUR8InycSpmf9ZtSCfN69lgojeOoucD7fU9cjxAt4raFBTTgSo34gD5lSZ83Klb1k?w=500&auto=format",
    "cast_date": "2023-11-08T22:46:05.000Z",
    "text": "hmu if you make art and want to start earning recurring revenue onchain. we're gearing up to launch hypersub, our artist-oriented implementation of STP\n\ncontext: https://warpcast.com/nonlinear.eth/0x8f7c01f0",
    "embeds": [
      {
        "url": "https://i.imgur.com/RV8Ej3c.png",
        "metadata": {
          "content_type": "image/png",
          "content_length": 301364,
          "_status": "RESOLVED",
          "image": {
            "width_px": 1852,
            "height_px": 1804
          }
        }
      },
      {
        "url": "https://warpcast.com/nonlinear.eth/0x8f7c01f0",
        "metadata": {
          "content_type": "text/html;charset=utf-8",
          "content_length": null,
          "_status": "RESOLVED",
          "html": {
            "ogUrl": "https://warpcast.com/nonlinear.eth/0x8f7c01f0",
            "ogType": "article",
            "favicon": "/favicon.png",
            "ogImage": [
              {
                "url": "https://client.warpcast.com/v2/og-image?castHash=0x8f7c01f0e4b86797d0f22747a4c9d33327ef4e00",
                "width": "1200",
                "height": "630"
              }
            ],
            "ogTitle": "Jonny Mack on Warpcast",
            "ogLocale": "en",
            "ogSiteName": "Warpcast",
            "ogDescription": "excited to announce STP: the Subscription Token Protocol\n\nits an extension of the ERC-721 NFT standard, with a temporal dimension and economic incentives for distribution, adoption, growth, and retention https://i.imgur.com/lU75TYU.png https://blog.withfabric.xyz/stp"
          }
        }
      }
    ],
    "enrichment_status": "SUCCESS"
  },
  {
    "cast_hash": "0x9d54fab3",
    "url": "https://warpcast.com/jessepollak.eth/0x9d54fab3",
    "author_username": "jessepollak.eth",
    "show_date": "2024-01-04",
    "show_title": "GM Farcaster ep23 Nov 10, 2023",
    "source_episode_id": "N0s6TwJ_IWE",
    "author_fid": 99,
    "author_pfp": "https://tba-mobile.mypinata.cloud/ipfs/QmdD5hZrJz1CDVLs2Tg5JLnNR8hjWFVZmMqVWRAWoWYFJd?pinataGatewayToken=3nq0UVhtd3rYmgYDdb1I9qv7rHsw-_DzwdWkZPRQ-QW1avFI9dCS8knaSfq_R5_q",
    "cast_date": "2023-11-09T20:48:53.000Z",
    "text": "coinbase just launched onchain verifications on the ethereum attestation service on @base.base.eth - really powerful tool for anyone building onchain\n\none more way we're using open source, public good infrastructure to enable the next billion users to come onchain\n\nhttps://x.com/CoinbaseCloud/status/1722702330406060282?s=20",
    "embeds": [
      {
        "url": "https://x.com/CoinbaseCloud/status/1722702330406060282?s=20",
        "metadata": {
          "content_type": "text/html;charset=utf-8",
          "content_length": null,
          "_status": "RESOLVED",
          "html": {
            "oembed": {
              "url": "https://twitter.com/CoinbaseDev/status/1722702330406060282",
              "html": "<blockquote class=\"twitter-tweet\"><p lang=\"en\" dir=\"ltr\">Introducing Coinbase verifications – Users can attest to account and country credentials onchain, all verified by Coinbase, now live for our 100M+ users at <a href=\"https://t.co/MhBwIpmwEv\">https://t.co/MhBwIpmwEv</a> <a href=\"https://t.co/gBuw7gmkw1\">pic.twitter.com/gBuw7gmkw1</a></p>&mdash; Coinbase Developer Platform🛡️ (@CoinbaseDev) <a href=\"https://twitter.com/CoinbaseDev/status/1722702330406060282?ref_src=twsrc%5Etfw\">November 9, 2023</a></blockquote>\n<script async src=\"https://platform.twitter.com/widgets.js\" charset=\"utf-8\"></script>\n\n",
              "type": "rich",
              "width": 550,
              "height": null,
              "method": "provider-api",
              "version": "1.0",
              "cache_age": "3153600000",
              "author_url": "https://twitter.com/CoinbaseDev",
              "author_name": "Coinbase Developer Platform🛡️",
              "provider_url": "https://twitter.com",
              "provider_name": "Twitter"
            },
            "favicon": "//abs.twimg.com/favicons/twitter.3.ico",
            "ogImage": [
              {
                "url": "https://abs-0.twimg.com/emoji/v2/svg/26a0.svg",
                "type": "svg"
              }
            ],
            "ogLocale": "en",
            "ogSiteName": "X (formerly Twitter)"
          }
        }
      }
    ],
    "enrichment_status": "SUCCESS"
  },
  {
    "cast_hash": "0xaee420cf",
    "url": "https://warpcast.com/linda/0xaee420cf",
    "author_username": "linda",
    "show_date": "2024-01-04",
    "show_title": "GM Farcaster ep23 Nov 10, 2023",
    "source_episode_id": "N0s6TwJ_IWE",
    "author_fid": 12,
    "author_pfp": "https://imagedelivery.net/BXluQx4ige9GuW0Ia56BHw/6aa18817-6238-4b25-086f-1edd0c438f00/original",
    "cast_date": "2023-11-09T05:10:31.000Z",
    "text": "Wanted to give a shout out to @neynar for being great to work with. The team is super responsive and on top of things. It made building Bountycaster so much easier for me and @pirosb3 🙌",
    "embeds": [],
    "enrichment_status": "SUCCESS"
  },
  {
    "cast_hash": "0x36085490",
    "url": "https://warpcast.com/dylsteck.eth/0x36085490",
    "author_username": "dylsteck.eth",
    "show_date": "2024-01-04",
    "show_title": "GM Farcaster ep23 Nov 10, 2023",
    "source_episode_id": "N0s6TwJ_IWE",
    "author_fid": 616,
    "author_pfp": "https://zku9gdedgba48lmr.public.blob.vercel-storage.com/basenames/avatar/dylsteck.base.eth/1724182478110/ds-logo-white-bg-LjfhiIB4NhZTVF0hTjv3E87lih5Qbu.png",
    "cast_date": "2023-11-10T00:36:01.000Z",
    "text": "So excited to unveil Farcaster Kit — React hooks for the best Farcaster apps\n\nOur hooks and free API(backed by the official replicator) let you easily build and manage your Farcaster app\n\nStart building at farcasterkit.com, or npm install farcasterkit\n\nhttps://youtu.be/ITzUr3haE8I?si=M02LTwACtxJEHGwx",
    "embeds": [
      {
        "url": "https://youtu.be/ITzUr3haE8I?si=M02LTwACtxJEHGwx",
        "metadata": {
          "content_type": "text/html; charset=utf-8",
          "content_length": 825810,
          "_status": "RESOLVED"
        }
      }
    ],
    "enrichment_status": "SUCCESS"
  },
  {
    "cast_hash": "0x561bf0eb",
    "url": "https://warpcast.com/dylsteck.eth/0x561bf0eb",
    "author_username": "dylsteck.eth",
    "show_date": "2024-01-04",
    "show_title": "GM Farcaster ep23 Nov 10, 2023",
    "source_episode_id": "N0s6TwJ_IWE",
    "author_fid": 616,
    "author_pfp": "https://zku9gdedgba48lmr.public.blob.vercel-storage.com/basenames/avatar/dylsteck.base.eth/1724182478110/ds-logo-white-bg-LjfhiIB4NhZTVF0hTjv3E87lih5Qbu.png",
    "cast_date": "2023-11-09T18:00:54.000Z",
    "text": "Live casting the Farcaster Dev Call, which is about to start 🫡\n\nhttps://warpcast.com/v/0x71a6763b",
    "embeds": [
      {
        "url": "https://warpcast.com/v/0x71a6763b",
        "metadata": {
          "content_type": "text/html;charset=utf-8",
          "content_length": null,
          "_status": "RESOLVED",
          "html": {
            "ogUrl": "https://warpcast.com/v/0x71a6763b",
            "ogType": "article",
            "favicon": "/favicon.png",
            "ogImage": [
              {
                "url": "https://client.warpcast.com/v2/og-image?castHash=0x71a6763bc2585c94c84ffd9abc719c621d710da0",
                "width": "1200",
                "height": "630"
              }
            ],
            "ogTitle": "Varun Srinivasan on Warpcast",
            "ogLocale": "en",
            "ogSiteName": "Warpcast",
            "ogDescription": "Farcaster Nov 9th Dev Call! \n\n- FIP-10\n- Replicator Updates\n- Farcaster Connect\n- Web Passkeys\n- Warps\n\nStarts in ~ 12 mins https://warpcast.notion.site/Nov-9th-7ac26c339be64c36b479438bb81d7d24?pvs=4"
          }
        }
      }
    ],
    "enrichment_status": "SUCCESS"
  },
  {
    "cast_hash": "0x4581ed94",
    "url": "https://warpcast.com/grin/0x4581ed94",
    "author_username": "grin",
    "show_date": "2024-01-04",
    "show_title": "GM Farcaster ep23 Nov 10, 2023",
    "source_episode_id": "N0s6TwJ_IWE",
    "author_fid": 1970,
    "author_pfp": "https://imagedelivery.net/BXluQx4ige9GuW0Ia56BHw/e8d65d0e-42de-4237-1159-128e81c94900/original",
    "cast_date": "2023-11-09T14:21:15.000Z",
    "text": "after the first FarCon, @cameron and I knew we couldn't run them all ourselves\n\nFC is a decentralized protocol and it demands a decentralized conference\n\nthat, and when Michael Jordan's open, you *pass the rock*\n\nso I'm delighted to present your hosts for FarCon 2024: @ted and @mcbain 🙌\n\nmore info from them soon",
    "embeds": [],
    "enrichment_status": "SUCCESS"
  },
  {
    "cast_hash": "0x4d983821",
    "url": "https://warpcast.com/nounishprof/0x4d983821",
    "author_username": "nounishprof",
    "show_date": "2024-01-04",
    "show_title": "GM Farcaster ep23 Nov 10, 2023",
    "source_episode_id": "N0s6TwJ_IWE",
    "enrichment_status": "FAILED",
    "enrichment_status_code": 404
  },
  {
    "cast_hash": "0xee61823a",
    "url": "https://warpcast.com/dwr.eth/0xee61823a",
    "author_username": "dwr.eth",
    "show_date": "2024-01-04",
    "show_title": "GM Farcaster ep23 Nov 10, 2023",
    "source_episode_id": "N0s6TwJ_IWE",
    "author_fid": 3,
    "author_pfp": "https://imagedelivery.net/BXluQx4ige9GuW0Ia56BHw/bc698287-5adc-4cc5-a503-de16963ed900/original",
    "cast_date": "2023-11-09T17:02:13.000Z",
    "text": "\"Why didn't I get warps?\"\n\n- We're granting warps to users for retroactive behavior that we believed benefitted the protocol\n\n- Key word here is retroactive—so if you meet the criteria later, you don't qualify for a previous grant\n\n- We take into account other users reports of spam / inappropriate and disqualify",
    "embeds": [],
    "enrichment_status": "SUCCESS"
  },
  {
    "cast_hash": "0xfb298eb2",
    "url": "https://warpcast.com/dwr.eth/0xfb298eb2",
    "author_username": "dwr.eth",
    "show_date": "2024-01-04",
    "show_title": "GM Farcaster ep23 Nov 10, 2023",
    "source_episode_id": "N0s6TwJ_IWE",
    "author_fid": 3,
    "author_pfp": "https://imagedelivery.net/BXluQx4ige9GuW0Ia56BHw/bc698287-5adc-4cc5-a503-de16963ed900/original",
    "cast_date": "2023-11-09T18:59:04.000Z",
    "text": "What are Warps?\n\nSimple: Makes it easier to add a Farcaster app.\n\nAdvanced: Another way to pay to connect a Farcaster app (which has an underlying onchain transaction) that is not an in-app $0.99 payment but is compliant with App Store rules.\n\nhttps://warpcast.notion.site/Warps-ea98989b8a944a679c5b9e076e07efcd",
    "embeds": [
      {
        "url": "https://warpcast.notion.site/Warps-ea98989b8a944a679c5b9e076e07efcd",
        "metadata": {
          "content_type": "text/html;charset=utf-8",
          "content_length": null,
          "_status": "RESOLVED",
          "html": {
            "ogUrl": "https://warpcast.notion.site/Warps-ea98989b8a944a679c5b9e076e07efcd",
            "ogType": "article",
            "favicon": "https://warpcast.notion.site/image/https%3A%2F%2Fprod-files-secure.s3.us-west-2.amazonaws.com%2F1ae150b5-547b-47f9-9f29-638305dbba7a%2Fff541562-dece-4188-8af0-3a66aeaf3e05%2FScreenshot_2023-10-27_at_3.00.44_PM_(1).png?table=block&id=ea98989b-8a94-4a67-9c5b-9e076e07efcd&spaceId=1ae150b5-547b-47f9-9f29-638305dbba7a&width=2000&userId=&cache=v2",
            "ogImage": [
              {
                "url": "https://warpcast.notion.site/images/meta/notion-wordmark.png",
                "type": "png"
              }
            ],
            "ogTitle": "Warps | Notion",
            "ogLocale": "en_US",
            "ogSiteName": "Warpcast on Notion",
            "ogDescription": "Last updated February 14, 2024"
          }
        }
      }
    ],
    "enrichment_status": "SUCCESS"
  },
  {
    "cast_hash": "0x39722917",
    "url": "https://warpcast.com/lsankar.eth/0x39722917",
    "author_username": "lsankar.eth",
    "show_date": "2024-01-04",
    "show_title": "GM Farcaster ep23 Nov 10, 2023",
    "source_episode_id": "N0s6TwJ_IWE",
    "author_fid": 54,
    "author_pfp": "https://i.imgur.com/tkJCeQo.jpg",
    "cast_date": "2023-11-08T02:27:39.000Z",
    "text": "added a static list of all fc owners who owned cryptokitties in 2019 to https://mintcaster.creddd.xyz/\n\ncc @frdysk",
    "embeds": [
      {
        "url": "https://i.imgur.com/OHwSe7X.png",
        "metadata": {
          "content_type": "image/png",
          "content_length": 193569,
          "_status": "RESOLVED",
          "image": {
            "width_px": 1270,
            "height_px": 1356
          }
        }
      },
      {
        "url": "https://mintcaster.creddd.xyz/",
        "metadata": {
          "content_type": null,
          "content_length": null,
          "_status": "RESOLVED"
        }
      }
    ],
    "enrichment_status": "SUCCESS"
  },
  {
    "cast_hash": "0xaa311108",
    "url": "https://warpcast.com/balajis.eth/0xaa311108",
    "author_username": "balajis.eth",
    "show_date": "2024-01-04",
    "show_title": "GM Farcaster ep23 Nov 10, 2023",
    "source_episode_id": "N0s6TwJ_IWE",
    "author_fid": 37,
    "author_pfp": "https://github.com/balajis.png",
    "cast_date": "2023-11-10T11:42:41.000Z",
    "text": "I have ideas on next steps after the Network State conference.\n\nBut I’m interested in yours. What’s next?",
    "embeds": [],
    "enrichment_status": "SUCCESS"
  }
]